hide_n_seek/__init__.py
hide_n_seek-0.0.1.dist-info/LICENSE.txt
hide_n_seek-0.0.1.dist-info/METADATA
hide_n_seek-0.0.1.dist-info/WHEEL
hide_n_seek-0.0.1.dist-info/top_level.txt
hide_n_seek-0.0.1.dist-info/RECORD
