Metadata-Version: 2.1
Name: hide-n-seek
Version: 0.0.1
Summary: Hide n seek Something Intresting.
Home-page: https://github.com/mr-ahir-is-here
Author: Amit
Author-email: haddbtc@example.com
License: UNKNOWN
Platform: UNKNOWN
Classifier: Programming Language :: Python :: 3
Classifier: License :: OSI Approved :: MIT License
Classifier: Operating System :: OS Independent
Requires-Python: >=3.6
